setup.py
balistem/__init__.py
balistem/stemmer.py
balistem.egg-info/PKG-INFO
balistem.egg-info/SOURCES.txt
balistem.egg-info/dependency_links.txt
balistem.egg-info/top_level.txt