Metadata-Version: 1.0
Name: balistem
Version: 0.1
Summary: An example of a python package from pre-existing code
Home-page: https://github.com/putuwaw/balistem
Author: Putu Widyantara
Author-email: putuwaw973@gmail.com
License: MIT
Platform: UNKNOWN
